odoo10_addon_website_no_crawler-10.0.1.0.0-py2.7-nspkg.pth
odoo10_addon_website_no_crawler-10.0.1.0.0.dist-info/top_level.txt
odoo10_addon_website_no_crawler-10.0.1.0.0.dist-info/WHEEL
odoo10_addon_website_no_crawler-10.0.1.0.0.dist-info/RECORD
odoo10_addon_website_no_crawler-10.0.1.0.0.dist-info/metadata.json
odoo10_addon_website_no_crawler-10.0.1.0.0.dist-info/DESCRIPTION.rst
odoo10_addon_website_no_crawler-10.0.1.0.0.dist-info/METADATA
odoo10_addon_website_no_crawler-10.0.1.0.0.dist-info/namespace_packages.txt
odoo/addons/website_no_crawler/__manifest__.py
odoo/addons/website_no_crawler/__init__.py
odoo/addons/website_no_crawler/README.rst
odoo/addons/website_no_crawler/views/disable_robots.xml
odoo/addons/website_no_crawler/static/description/icon.png
