Metadata-Version: 2.0
Name: odoo10-addon-website-no-crawler
Version: 10.0.1.0.0
Summary: Disables robots.txt for indexing by webcrawlers like Google
Home-page: UNKNOWN
Author: B-Informed B.V.,Odoo Community Association (OCA)
Author-email: support@odoo-community.org
License: AGPL-3
Platform: UNKNOWN
Requires-Dist: odoo (<10.1dev,>=10.0)
Classifier: Programming Language :: Python :: 2.7
Classifier: Framework :: Odoo
Classifier: License :: OSI Approved :: GNU Affero General Public License v3
